dcx/__init__.py
dcx/__main__.py
dcx-0.104.0.dist-info/licenses/LICENSE
dcx-0.104.0.dist-info/METADATA
dcx-0.104.0.dist-info/WHEEL
dcx-0.104.0.dist-info/top_level.txt
dcx-0.104.0.dist-info/RECORD
