Metadata-Version: 2.4
Name: dcx
Version: 0.104.0
Summary: Minimalistic selenium wrapper
Author-email: Robert Degen <turbodev@mailbox.org>
Project-URL: Homepage, https://github.com/turbo-bert/dcx
Project-URL: Issues, https://github.com/turbo-bert/dcx/issues
Classifier: Programming Language :: Python :: 3
Classifier: License :: OSI Approved :: MIT License
Classifier: Operating System :: OS Independent
Requires-Python: >=3.8
License-File: LICENSE
Requires-Dist: reportlab
Requires-Dist: requests
Requires-Dist: selenium
Requires-Dist: rich
Requires-Dist: turbowriter>=0.0.4
Requires-Dist: turbodinwriter
Requires-Dist: pillow
Requires-Dist: tabulate
Dynamic: license-file
